setup.py
papitools/__init__.py
papitools/papitools.py
papitools.egg-info/PKG-INFO
papitools.egg-info/SOURCES.txt
papitools.egg-info/dependency_links.txt
papitools.egg-info/namespace_packages.txt
papitools.egg-info/top_level.txt