Metadata-Version: 1.0
Name: papitools
Version: 0.10
Summary: This package is to a wrapper to PAPI framework at akamai
Home-page: https://github.com/vreddhi/PAPITools
Author: Vreddhi
Author-email: vreddhi.bhat@gmail.com
License: MIT
Keywords: PAPI akamai Property Manager
Platform: UNKNOWN
